source/__init__.py
source/calculator.py
tests/__init__.py
tests/test_calculator.py
og_calculator_1234-0.0.4.dist-info/LICENSE
og_calculator_1234-0.0.4.dist-info/METADATA
og_calculator_1234-0.0.4.dist-info/WHEEL
og_calculator_1234-0.0.4.dist-info/entry_points.txt
og_calculator_1234-0.0.4.dist-info/top_level.txt
og_calculator_1234-0.0.4.dist-info/RECORD
